enpi_api/__init__.py
enpi_api/l1/__init__.py
enpi_api/l1/openapi_client/__init__.py
enpi_api/l1/openapi_client/api_client.py
enpi_api/l1/openapi_client/api_response.py
enpi_api/l1/openapi_client/configuration.py
enpi_api/l1/openapi_client/exceptions.py
enpi_api/l1/openapi_client/rest.py
enpi_api/l1/openapi_client/api/__init__.py
enpi_api/l1/openapi_client/api/basket_api.py
enpi_api/l1/openapi_client/api/cluster_api.py
enpi_api/l1/openapi_client/api/collection_api.py
enpi_api/l1/openapi_client/api/enrichment_api.py
enpi_api/l1/openapi_client/api/file_api.py
enpi_api/l1/openapi_client/api/filter_api.py
enpi_api/l1/openapi_client/api/liabilities_api.py
enpi_api/l1/openapi_client/api/ml_api.py
enpi_api/l1/openapi_client/api/phylogeny_api.py
enpi_api/l1/openapi_client/api/reference_database_api.py
enpi_api/l1/openapi_client/api/sequence_annotation_api.py
enpi_api/l1/openapi_client/api/tag_api.py
enpi_api/l1/openapi_client/api/whoami_api.py
enpi_api/l1/openapi_client/api/workflow_api.py
enpi_api/l1/openapi_client/models/__init__.py
enpi_api/l1/openapi_client/models/add_clones_bad_reqeust_response.py
enpi_api/l1/openapi_client/models/add_clones_not_found_response.py
enpi_api/l1/openapi_client/models/add_clones_request_body.py
enpi_api/l1/openapi_client/models/and_operator.py
enpi_api/l1/openapi_client/models/and_operator_conditions_inner.py
enpi_api/l1/openapi_client/models/basket.py
enpi_api/l1/openapi_client/models/clone_annotation.py
enpi_api/l1/openapi_client/models/clone_annotation1.py
enpi_api/l1/openapi_client/models/clone_id_to_tag_spec.py
enpi_api/l1/openapi_client/models/cluster_additional_options.py
enpi_api/l1/openapi_client/models/cluster_run.py
enpi_api/l1/openapi_client/models/cluster_run_not_found_response.py
enpi_api/l1/openapi_client/models/cluster_work.py
enpi_api/l1/openapi_client/models/collection_annotation.py
enpi_api/l1/openapi_client/models/collection_annotation1.py
enpi_api/l1/openapi_client/models/collection_annotation1_tags_inner.py
enpicom_sdk-1.5.2.dist-info/METADATA
enpicom_sdk-1.5.2.dist-info/WHEEL
enpicom_sdk-1.5.2.dist-info/entry_points.txt
enpicom_sdk-1.5.2.dist-info/top_level.txt
enpicom_sdk-1.5.2.dist-info/RECORD
