Metadata-Version: 2.1
Name: enpicom-sdk
Version: 1.5.2
Summary: SDK for interacting with the ENPICOM Platform
Requires-Python: >=3.11
Requires-Dist: loguru>=0.7.2
Requires-Dist: requests>=2.31.0
Requires-Dist: types-requests>=2.31.0
Requires-Dist: mypy==1.10.1
Requires-Dist: types-python-dateutil>=2.9.0.20240316
Requires-Dist: pdoc>=14.4.0
Requires-Dist: tqdm>=4.66.2
Requires-Dist: types-tqdm>=4.64.0
Requires-Dist: paho-mqtt>=2.1.0
Requires-Dist: pandas>=2
Requires-Dist: pandas-stubs>=2
Requires-Dist: boto3>=1.34.79
Requires-Dist: boto3-stubs[essential]>=1.34.79
Requires-Dist: jupytext>=1.16.4
Requires-Dist: build>=1.2.1
Requires-Dist: python-dateutil>=2.5.3
Requires-Dist: setuptools>=21.0.0
Requires-Dist: urllib3>=1.25.3
Requires-Dist: pydantic>=2
Requires-Dist: typing-extensions>=4.7.1
Requires-Dist: mlflow-skinny==2.20.0
Requires-Dist: scipy>=1.14.0
